SimpleNetMNIST/predict.py
SimpleNetMNIST/simpnet.py
SimpleNetMNIST/train.py
SimpleNetMNIST/utils.py
SimpleNetMNIST-1.0.4.dist-info/LICENSE
SimpleNetMNIST-1.0.4.dist-info/METADATA
SimpleNetMNIST-1.0.4.dist-info/WHEEL
SimpleNetMNIST-1.0.4.dist-info/top_level.txt
SimpleNetMNIST-1.0.4.dist-info/RECORD
