Metadata-Version: 2.1
Name: SimpleNetMNIST
Version: 1.0.4
Summary: SimpleNetMNIST.  Based off an implementation of a simple neural network for MNIST classification in PyTorch. Created by Edward Ji (https://github.com/Edward-Ji).
Author-email: Edward Ji <jiziao6@gmail.com>, Daniel Elliott <danelliottster@gmail.com>
License: MIT License
Project-URL: homepage, https://github.com/danelliottster/SimpleNetMNIST
Keywords: pytorch,mnist,neural network
Classifier: License :: OSI Approved :: MIT License
Classifier: Programming Language :: Python
Classifier: Programming Language :: Python :: 3
Requires-Python: >=3.8
License-File: LICENSE
Requires-Dist: torch >=2.0
